deserealization/__init__.py
deserealization/main.py
deserealization/typing.py
deserealization/json_to_object/__init__.py
deserealization/json_to_object/json_mapping.py
deserealization/json_to_object/common/__init__.py
deserealization/json_to_object/common/abstract_apply_mapping.py
deserealization/json_to_object/common/data_validation_applementation.py
deserealization/json_to_object/contract/__init__.py
deserealization/json_to_object/contract/interface_json_to_object.py
deserealization/json_to_object/contract/interface_mapping.py
deserealization/json_to_object/implementation/__init__.py
deserealization/json_to_object/implementation/generic_json2object.py
deserealization/json_to_object/implementation/json2object.py
deserealization/json_to_object/implementation/json2object_factory.py
deserealization/usecase/__init__.py
deserealization/usecase/map_json.py
deserealization/usecase/map_json_without_init.py
json_deserializer_to_object-0.0.2.dist-info/METADATA
json_deserializer_to_object-0.0.2.dist-info/WHEEL
json_deserializer_to_object-0.0.2.dist-info/top_level.txt
json_deserializer_to_object-0.0.2.dist-info/RECORD
