Metadata-Version: 2.1
Name: json-deserializer-to-object
Version: 0.0.2
Summary: Small library utils
Author: Andrianarivo
Author-email: tantelitiana22@gmail.com
Classifier: Programming Language :: Python :: 3
Classifier: License :: OSI Approved :: MIT License
Classifier: Operating System :: OS Independent
Requires-Python: >=3.6
